Metadata-Version: 2.1
Name: Mixiis-Calculator
Version: 1.0.0
Summary: Makes Standard Calculations
Home-page: https://github.com/Mixiir/Calculator
Author: Mikk Narusberg
Author-email: mikk.narusberg@gmail.com
License: MIT
Platform: Python
License-File: License.txt
